MANIFEST.in
README.rst
prova.py
requirements.txt
setup.py
this.py
accrocchio/__init__.py
accrocchio/badgeofshame.py
accrocchio/observers.py
accrocchio.egg-info/PKG-INFO
accrocchio.egg-info/SOURCES.txt
accrocchio.egg-info/dependency_links.txt
accrocchio.egg-info/not-zip-safe
accrocchio.egg-info/requires.txt
accrocchio.egg-info/top_level.txt