Metadata-Version: 1.1
Name: accrocchio
Version: 0.1.13
Summary: Accrocchio is a library to mark and being notified of smelly code (a.k.a, "accrocchio").
Home-page: https://github.com/fcracker79/accrocchio
Author: fcracker79
Author-email: fcracker79@gmail.com
License: MIT
Keywords: accrocchio hinting linting qa design patterns resign
Platform: UNKNOWN
Classifier: Development Status :: 4 - Beta
Classifier: Intended Audience :: Developers
Classifier: Topic :: Software Development
Classifier: License :: OSI Approved :: MIT License
Classifier: Programming Language :: Python :: 3.5
